opensubmit/__init__.py
opensubmit/app.py
opensubmit/cmdline.py
opensubmit/contextprocessors.py
opensubmit/dashboard.py
opensubmit/forms.py
opensubmit/mails.py
opensubmit/middleware.py
opensubmit/security.py
opensubmit/settings.py
opensubmit/signalhandlers.py
opensubmit/urls.py
opensubmit/wsgi.py
opensubmit/admin/__init__.py
opensubmit/admin/assignment.py
opensubmit/admin/course.py
opensubmit/admin/grading.py
opensubmit/admin/gradingscheme.py
opensubmit/admin/studyprogram.py
opensubmit/admin/submission.py
opensubmit/admin/submissionfile.py
opensubmit/admin/user.py
opensubmit/management/commands/__init__.py
opensubmit/management/commands/democreate.py
opensubmit/management/commands/dumpconfig.py
opensubmit/management/commands/fixchecksums.py
opensubmit/management/commands/fixperms.py
opensubmit/management/commands/makeadmin.py
opensubmit/management/commands/makeowner.py
opensubmit/management/commands/makestudent.py
opensubmit/management/commands/maketutor.py
opensubmit/migrations/0001_initial.py
opensubmit/migrations/0002_auto_20141208_1122.py
opensubmit/migrations/0003_auto_20150831_1900.py
opensubmit/migrations/0004_auto_20150923_1356.py
opensubmit/migrations/0005_auto_20151007_2253.py
opensubmit/migrations/0006_testmachine_address.py
opensubmit/migrations/0007_auto_20151007_2322.py
opensubmit/migrations/0008_submissionfile_md5.py
opensubmit/migrations/0009_auto_20151127_1722.py
opensubmit/migrations/0010_auto_20160413_1224.py
opensubmit/migrations/0011_auto_20160413_1302.py
opensubmit/migrations/0012_auto_20160601_1413.py
opensubmit/migrations/0013_assignment_test_compile_files.py
opensubmit/migrations/0014_auto_20161103_2050.py
opensubmit/migrations/0015_auto_20161103_2205.py
opensubmit/migrations/0016_auto_20171010_0946.py
opensubmit/migrations/0017_auto_20171010_1037.py
opensubmit/migrations/0018_assignment_description.py
opensubmit/migrations/0019_auto_20171011_2103.py
opensubmit_web-0.7.17.dist-info/METADATA
opensubmit_web-0.7.17.dist-info/RECORD
opensubmit_web-0.7.17.dist-info/WHEEL
opensubmit_web-0.7.17.dist-info/entry_points.txt
opensubmit_web-0.7.17.dist-info/top_level.txt
