Metadata-Version: 2.1
Name: opensubmit-web
Version: 0.7.17
Summary: A web application for managing student assignment solutions in a university environment.
Home-page: https://github.com/troeger/opensubmit
Author: Peter Tröger
Author-email: peter@troeger.eu
License: AGPL
Platform: UNKNOWN
Classifier: Development Status :: 4 - Beta
Classifier: Programming Language :: Python :: 3.4
Classifier: Programming Language :: Python :: 3.5
Classifier: Programming Language :: Python :: 3.6
Requires-Dist: Django (<1.12,>=1.11)
Requires-Dist: django-bootstrap-form
Requires-Dist: djangorestframework (>=2.4)
Requires-Dist: django-grappelli (>=2.8.1)
Requires-Dist: django-formtools
Requires-Dist: requests (>=2.5.1)
Requires-Dist: social-auth-app-django
Requires-Dist: python3-openid
Requires-Dist: python-oauth2
Requires-Dist: oauthlib (>=0.6.2)
Requires-Dist: pyjwkest (>=1.4.0)
Requires-Dist: lti
